nonebot_plugin_deer_pipe/__init__.py
nonebot_plugin_deer_pipe/constants.py
nonebot_plugin_deer_pipe/database.py
nonebot_plugin_deer_pipe/image.py
nonebot_plugin_deer_pipe/matchers.py
nonebot_plugin_deer_pipe/py.typed
nonebot_plugin_deer_pipe/requirements.py
nonebot_plugin_deer_pipe/assets/MiSans-Regular.ttf
nonebot_plugin_deer_pipe/assets/check@96x100.png
nonebot_plugin_deer_pipe/assets/deerpipe@100x82.png
nonebot_plugin_deer_pipe-0.4.1.dist-info/METADATA
nonebot_plugin_deer_pipe-0.4.1.dist-info/WHEEL
nonebot_plugin_deer_pipe-0.4.1.dist-info/licenses/LICENSE
nonebot_plugin_deer_pipe-0.4.1.dist-info/RECORD
