Metadata-Version: 2.3
Name: nonebot-plugin-deer-pipe
Version: 0.4.1
Summary: A deer-pipe attendance plugin for nonebot2
Project-URL: Homepage, https://github.com/SamuNatsu/nonebot-plugin-deer-pipe
Project-URL: Issues, https://github.com/SamuNatsu/nonebot-plugin-deer-pipe/issues
Author-email: SNRainiar <rainiar@foxmail.com>
License: AGPL-3.0-or-later
Classifier: License :: OSI Approved :: GNU Affero General Public License v3 or later (AGPLv3+)
Classifier: Operating System :: OS Independent
Classifier: Programming Language :: Python :: 3.10
Classifier: Typing :: Typed
Requires-Python: >=3.10
Requires-Dist: aiosqlite>=0.20.0
Requires-Dist: nonebot-plugin-alconna>=0.54.0
Requires-Dist: nonebot-plugin-apscheduler>=0.5.0
Requires-Dist: nonebot-plugin-localstore>=0.7.2
Requires-Dist: nonebot-plugin-userinfo>=0.2.6
Requires-Dist: nonebot2>=2.4.0
Requires-Dist: pillow>=11.0.0
Requires-Dist: sqlmodel>=0.0.22
